drawsvg_helper_micro/__init__.py
drawsvg_helper_micro/drawsvg_helper.py
drawsvg_helper_micro-0.1.0.dist-info/METADATA
drawsvg_helper_micro-0.1.0.dist-info/WHEEL
drawsvg_helper_micro-0.1.0.dist-info/licenses/LICENSE
drawsvg_helper_micro-0.1.0.dist-info/RECORD
