Metadata-Version: 2.3
Name: drawsvg_helper_micro
Version: 0.1.0
Summary: A wrapper class for drawsvg
Author: Samuel Shiels
License-File: LICENSE
Classifier: Development Status :: 3 - Alpha
Classifier: Environment :: Other Environment
Classifier: Intended Audience :: Developers
Classifier: Intended Audience :: System Administrators
Classifier: License :: OSI Approved :: MIT License
Classifier: Operating System :: POSIX :: Linux
Classifier: Programming Language :: Python :: 3
Classifier: Topic :: Utilities
Requires-Python: >=3.12.4
Requires-Dist: drawsvg
